Harvard_Central_Processing_Unit.srcs/sources_1/new/data_memory.v
`timescale 1ns / 1ps
//////////////////////////////////////////////////////////////////////////////////
// Company: 
// Engineer: 
// 
// Create Date: 09/29/2024 12:09:34 PM
// Design Name: 
// Module Name: data_memory
// Project Name: 
// Target Devices: 
// Tool Versions: 
// Description: 
// 
// Dependencies: 
// 
// Revision:
// Revision 0.01 - File Created
// Additional Comments:
// 
//////////////////////////////////////////////////////////////////////////////////


module data_memory (
    input wire clk,
    input wire [7:0] address,
    input wire write_enable,
    input wire read_enable,
    input wire [7:0] data_in,
    output reg [7:0] data_out
);

    reg [7:0] mem [0:255];

    integer i;

    initial begin
        // Initialize memory with some values
        for (i = 0; i < 256; i = i + 1) begin
            mem[i] = 8'd0;
        end
    end


//    always @(posedge clk) begin
//        // Read first (sees old value)
//        if (read_enable) begin
//            data_out = mem[address];  // Blocking assignment - happens immediately
//        end else begin
//            data_out = 8'd0;
//        end
//        // Write second (updates for next cycle)
//        if (write_enable) begin
//            mem[address] = data_in;   // Blocking assignment - happens after read
//        end
//    end
   always @(*) begin
     if (read_enable) begin
         data_out = mem[address];
     end else begin
         data_out = 8'd0;
     end
 end
 
 // Sequential write (on clock edge)
 always @(posedge clk) begin
     if (write_enable) begin
         mem[address] <= data_in;
     end
 end
    
    
//    always @(posedge clk) begin
//        if (write_enable) begin
//            mem[address] <= data_in;
//        end else         if (read_enable) begin
//                data_out <= mem[address];
//            end else begin
//                data_out <= 8'b0; 
//            end
//    end
    
//    always @* begin
//        if (read_enable) begin
//            data_out <= mem[address];
//        end else begin
//            data_out <= 8'b0; 
//        end
//    end

endmodule

Harvard_Central_Processing_Unit.srcs/sim_1/new/data_memory_tb.v
`timescale 1ns / 1ps
//////////////////////////////////////////////////////////////////////////////////
// Company: 
// Engineer: 
// 
// Create Date: 11/04/2024 09:45:48 PM
// Design Name: 
// Module Name: data_memory_tb
// Project Name: 
// Target Devices: 
// Tool Versions: 
// Description: 
// 
// Dependencies: 
// 
// Revision:
// Revision 0.01 - File Created
// Additional Comments:
// 
//////////////////////////////////////////////////////////////////////////////////

module data_memory_tb;

    // Inputs
    reg clk;
    reg [7:0] address;
    reg write_enable;
    reg read_enable;
    reg [7:0] data_in;

    // Outputs
    wire [7:0] data_out;

    // Instantiate the Unit Under Test (UUT)
    data_memory uut (
        .clk(clk),
        .address(address),
        .write_enable(write_enable),
        .read_enable(read_enable),
        .data_in(data_in),
        .data_out(data_out)
    );

    // Clock generation
    always begin
        #5 clk = ~clk;
    end

    initial begin
        // Initialize Inputs
        clk = 0;
        address = 0;
        write_enable = 0;
        read_enable = 0;
        data_in = 0;

        // Wait for global reset
        #10;
        
        // Test 1: Initial memory check (all zeros)
        $display("Test 1: Initial memory check");
        for (integer i = 0; i < 16; i = i + 1) begin
            address = i;
            read_enable = 1;
            #10;
            if (data_out !== 8'd0) begin
                $display("Error: Memory location %0d not initialized to 0", i);
                $finish;
            end
        end
        read_enable = 0;
        $display("Test 1 passed: All memory locations initialized to 0");
        
        // Test 2: Write and read test
        $display("\nTest 2: Write and read test");
        for (integer i = 0; i < 16; i = i + 1) begin
            address = i;
            data_in = 8'h55 + i;
            write_enable = 1;
            #10; // Write on posedge
            
            write_enable = 0;
            read_enable = 1;
            #10; // Read on next posedge
            
            if (data_out !== (8'h55 + i)) begin
                $display("Error: Write/read mismatch at address %0d", i);
                $display("Expected: %h, Got: %h", (8'h55 + i), data_out);
                $finish;
            end
        end
        read_enable = 0;
        $display("Test 2 passed: Write and read operations work correctly");
        
        // Test 3: Simultaneous write and read (should read old value)
        $display("\nTest 3: Simultaneous write and read");
        address = 8'h10;
        data_in = 8'hAA;
        write_enable = 1;
        read_enable = 1;
        #10;
        
        if (data_out !== 8'd0) begin
            $display("Error: Should read old value during simultaneous write");
            $display("Expected: 00, Got: %h", data_out);
            $finish;
        end
        
        // Check new value was written
        write_enable = 0;
        #10;
        if (data_out !== 8'hAA) begin
            $display("Error: New value not written properly");
            $display("Expected: AA, Got: %h", data_out);
            $finish;
        end
        read_enable = 0;
        $display("Test 3 passed: Simultaneous write/read behavior correct");
        
        // Test 4: Write without read enable
        $display("\nTest 4: Write without read enable");
        address = 8'h20;
        data_in = 8'hBB;
        write_enable = 1;
        read_enable = 0;
        #10;
        
        // Verify write occurred
        write_enable = 0;
        read_enable = 1;
        #10;
        if (data_out !== 8'hBB) begin
            $display("Error: Write without read enable failed");
            $display("Expected: BB, Got: %h", data_out);
            $finish;
        end
        read_enable = 0;
        $display("Test 4 passed: Write without read enable works");
        
        // Test 5: Read without write enable
        $display("\nTest 5: Read without write enable");
        address = 8'h10; // Should contain AA from Test 3
        write_enable = 0;
        read_enable = 1;
        #10;
        
        if (data_out !== 8'hAA) begin
            $display("Error: Read without write enable failed");
            $display("Expected: AA, Got: %h", data_out);
            $finish;
        end
        read_enable = 0;
        $display("Test 5 passed: Read without write enable works");
        
        // Test 6: No operation (both enables low)
        $display("\nTest 6: No operation test");
        address = 8'h10; // Contains AA
        write_enable = 0;
        read_enable = 0;
        #10;
        
        if (data_out !== 8'h00) begin
            $display("Error: Output should be high-Z when not reading");
            $display("Expected: 00, Got: %h", data_out);
            $finish;
        end
        $display("Test 6 passed: Output 0 when not reading");
        
        $display("\nAll data memory tests passed successfully");
        $finish;
    end

endmodule

//module data_memory_tb;
//    reg clk, write_enable, read_enable;
//    reg [7:0] address, data_in;
//    wire [7:0] data_out;
    
//    data_memory uut (
//        .clk(clk), .address(address), .write_enable(write_enable),
//        .read_enable(read_enable), .data_in(data_in), .data_out(data_out)
//    );
    
//    initial begin
//        clk = 0;
//        forever #5 clk = ~clk; // 10ns period
//    end
    
//    initial begin
//        $display("=== DATA MEMORY TESTBENCH ===");
        
//        // Initialize
//        write_enable = 0; read_enable = 0; address = 0; data_in = 0;
//        #20;
        
//        // Test 1: Initial memory check
//        $display("Test 1: Initial memory check");
//        address = 8'h10; read_enable = 1; #1;
//        if (data_out == 8'h00) 
//            $display("Test 1 passed: All memory locations initialized to 0");
//        else 
//            $display("Test 1 failed: Memory not initialized properly. Got: %h", data_out);
        
//        read_enable = 0; #10;
        
//        // Test 2: Write and read test
//        $display("Test 2: Write and read test");
        
//        // Write 0xAA to address 0x20
//        @(posedge clk);
//        address = 8'h20; data_in = 8'hAA; write_enable = 1;
//        @(posedge clk);
//        write_enable = 0;
        
//        // Read back from address 0x20
//        address = 8'h20; read_enable = 1; #1;
//        if (data_out == 8'hAA)
//            $display("Test 2 passed: Write and read operations work correctly");
//        else
//            $display("Test 2 failed: Expected AA, got %h", data_out);
        
//        read_enable = 0; #10;
        
//        // Test 3: Multiple locations
//        $display("Test 3: Multiple location test");
        
//        // Write to multiple locations
//        @(posedge clk);
//        address = 8'h30; data_in = 8'h11; write_enable = 1;
//        @(posedge clk);
//        address = 8'h31; data_in = 8'h22;
//        @(posedge clk);
//        address = 8'h32; data_in = 8'h33;
//        @(posedge clk);
//        write_enable = 0;
        
//        // Read back all locations
//        address = 8'h30; read_enable = 1; #1;
//        $display("Address 30: Expected 11, Got %h %s", data_out, 
//                (data_out == 8'h11) ? "PASS" : "FAIL");
        
//        address = 8'h31; #1;
//        $display("Address 31: Expected 22, Got %h %s", data_out,
//                (data_out == 8'h22) ? "PASS" : "FAIL");
        
//        address = 8'h32; #1;
//        $display("Address 32: Expected 33, Got %h %s", data_out,
//                (data_out == 8'h33) ? "PASS" : "FAIL");
        
//        read_enable = 0; #10;
        
//        // Test 4: Simultaneous write and read (critical timing test)
//        $display("Test 4: Simultaneous write and read");
        
//        // First, write a known value to address 0x40
//        @(posedge clk);
//        address = 8'h40; data_in = 8'h55; write_enable = 1;
//        @(posedge clk);
//        write_enable = 0;
        
//        // Verify it was written
//        address = 8'h40; read_enable = 1; #1;
//        $display("Pre-test: Address 40 contains %h (should be 55)", data_out);
        
//        // Now the critical test: simultaneous write and read
//        @(posedge clk);
//        $display("Before simultaneous operation: data_out = %h", data_out);
        
//        // On the same clock edge: try to write new value AND read
//        address = 8'h40; data_in = 8'h99; write_enable = 1; read_enable = 1;
        
//        // Check immediately (should see OLD value)
//        #1;
//        $display("During simultaneous write/read: data_out = %h", data_out);
//        if (data_out == 8'h55)
//            $display("Test 4 passed: Read returns old value during simultaneous write");
//        else
//            $display("Test 4 failed: Should read old value (55) during simultaneous write, got %h", data_out);
        
//        @(posedge clk);
//        write_enable = 0;
        
//        // Verify new value was written
//        #1;
//        $display("After write cycle: data_out = %h (should be 99)", data_out);
        
//        read_enable = 0; #10;
        
//        // Test 5: Read enable functionality
//        $display("Test 5: Read enable functionality");
        
//        // Write a value
//        @(posedge clk);
//        address = 8'h50; data_in = 8'hDD; write_enable = 1;
//        @(posedge clk);
//        write_enable = 0;
        
//        // Test with read_enable = 0
//        address = 8'h50; read_enable = 0; #1;
//        $display("With read_enable=0: data_out = %h (should be 00)", data_out);
//        if (data_out == 8'h00)
//            $display("Read disable works correctly");
//        else
//            $display("Read disable failed: Expected 00, got %h", data_out);
        
//        // Test with read_enable = 1
//        read_enable = 1; #1;
//        $display("With read_enable=1: data_out = %h (should be DD)", data_out);
//        if (data_out == 8'hDD)
//            $display("Read enable works correctly");
//        else
//            $display("Read enable failed: Expected DD, got %h", data_out);
        
//        read_enable = 0; #10;
        
//        // Test 6: Address range test
//        $display("Test 6: Address range test");
        
//        // Test boundary addresses
//        @(posedge clk);
//        address = 8'h00; data_in = 8'hF0; write_enable = 1;  // Address 0
//        @(posedge clk);
//        address = 8'hFF; data_in = 8'hF1;                    // Address 255
//        @(posedge clk);
//        write_enable = 0;
        
//        // Read back
//        address = 8'h00; read_enable = 1; #1;
//        $display("Address 00: Expected F0, Got %h %s", data_out,
//                (data_out == 8'hF0) ? "PASS" : "FAIL");
        
//        address = 8'hFF; #1;
//        $display("Address FF: Expected F1, Got %h %s", data_out,
//                (data_out == 8'hF1) ? "PASS" : "FAIL");
        
//        read_enable = 0;
        
//        $display("=== DATA MEMORY TEST COMPLETE ===");
//        #50; $finish;
//    end
    
//    // Monitor for debugging
//    always @(posedge clk) begin
//        if (write_enable || read_enable)
//            $display("Clock %0t: addr=%h, write=%b, read=%b, data_in=%h, data_out=%h",
//                    $time, address, write_enable, read_enable, data_in, data_out);
//    end
//endmodule

Harvard_Central_Processing_Unit.sim/sim_1/behav/xsim/data_memory_tb.vcd
$date
   Mon Nov  4 22:04:32 2024
$end
$version
  2018.2
$end
$timescale
  1ps
$end
$scope module data_memory_tb $end
$var reg 1 ! clk $end
$var reg 8 " address [7:0] $end
$var reg 1 # write_enable $end
$var reg 1 $ read_enable $end
$var reg 8 % data_in [7:0] $end
$var wire 8 & data_out [7:0] $end
$scope module dut $end
$var wire 1 ' clk $end
$var wire 8 ( address [7:0] $end
$var wire 1 ) write_enable $end
$var wire 1 * read_enable $end
$var wire 8 + data_in [7:0] $end
$var reg 8 , data_out [7:0] $end
$var integer 32 - i $end
$upscope $end
$upscope $end
$enddefinitions $end
#0
$dumpvars
0!
b0 "
0#
0$
b0 %
bx &
0'
b0 (
0)
0*
b0 +
bx ,
b100000000 -
$end
#5000
1!
1'
#10000
0!
0'
#15000
1!
1'
#20000
0!
b100000 "
1#
b10100101 %
0'
b100000 (
1)
b10100101 +
#25000
1!
1'
#30000
0!
0#
0'
0)
#35000
1!
1'
#40000
0!
0'
#45000
1!
1'
#50000
0!
1$
0'
1*
#55000
1!
b10100101 &
1'
b10100101 ,
#60000
0!
0'
#65000
1!
1'
#70000
0!
0'
#75000
1!
1'
#80000
0!
b1010101 "
1#
0$
b111100 %
0'
b1010101 (
1)
0*
b111100 +
#85000
1!
1'
#90000
0!
0#
0'
0)
#95000
1!
1'
#100000
0!
0'
#105000
1!
1'
#110000
0!
1$
0'
1*
#115000
1!
b111100 &
1'
b111100 ,
#120000
0!
0'
#125000
1!
1'
#130000
0!
0'
#135000
1!
1'
#140000
0!
b100000 "
0'
b100000 (
#145000
1!
b10100101 &
1'
b10100101 ,
#150000
0!
0'
#155000
1!
1'
#160000
0!
0'
#165000
1!
1'
#170000
0!
b1010101 "
0$
0'
b1010101 (
0*
#175000
1!
1'
#180000
0!
0'
#185000
1!
1'
#190000
0!
0'
#195000
1!
1'
#200000
0!
b100000 "
b11111111 %
0'
b100000 (
b11111111 +
#205000
1!
1$
1'
1*
