Harvard_Central_Processing_Unit.srcs/sources_1/new/data_memory.v
`timescale 1ns / 1ps
//////////////////////////////////////////////////////////////////////////////////
// Company: 
// Engineer: 
// 
// Create Date: 09/29/2024 12:09:34 PM
// Design Name: 
// Module Name: data_memory
// Project Name: 
// Target Devices: 
// Tool Versions: 
// Description: 
// 
// Dependencies: 
// 
// Revision:
// Revision 0.01 - File Created
// Additional Comments:
// 
//////////////////////////////////////////////////////////////////////////////////


module data_memory (
    input wire clk,
    input wire [7:0] address,
    input wire write_enable,
    input wire read_enable,
    input wire [7:0] data_in,
    output reg [7:0] data_out
);

    reg [7:0] mem [0:255];

    integer i;

    initial begin
        // Initialize memory with some values
        for (i = 0; i < 256; i = i + 1) begin
            mem[i] = 8'd0;
        end
    end


//    always @(posedge clk) begin
//        // Read first (sees old value)
//        if (read_enable) begin
//            data_out = mem[address];  // Blocking assignment - happens immediately
//        end else begin
//            data_out = 8'd0;
//        end
//        // Write second (updates for next cycle)
//        if (write_enable) begin
//            mem[address] = data_in;   // Blocking assignment - happens after read
//        end
//    end
   always @(*) begin
     if (read_enable) begin
         data_out = mem[address];
     end else begin
         data_out = 8'd0;
     end
 end
 
 // Sequential write (on clock edge)
 always @(posedge clk) begin
     if (write_enable) begin
         mem[address] <= data_in;
     end
 end
    
    
//    always @(posedge clk) begin
//        if (write_enable) begin
//            mem[address] <= data_in;
//        end else         if (read_enable) begin
//                data_out <= mem[address];
//            end else begin
//                data_out <= 8'b0; 
//            end
//    end
    
//    always @* begin
//        if (read_enable) begin
//            data_out <= mem[address];
//        end else begin
//            data_out <= 8'b0; 
//        end
//    end

endmodule

Harvard_Central_Processing_Unit.srcs/sim_1/new/data_memory_tb.v
`timescale 1ns / 1ps
//////////////////////////////////////////////////////////////////////////////////
// Company: 
// Engineer: 
// 
// Create Date: 11/04/2024 09:45:48 PM
// Design Name: 
// Module Name: data_memory_tb
// Project Name: 
// Target Devices: 
// Tool Versions: 
// Description: 
// 
// Dependencies: 
// 
// Revision:
// Revision 0.01 - File Created
// Additional Comments:
// 
//////////////////////////////////////////////////////////////////////////////////

module data_memory_tb();

    reg clk;
    reg [7:0] address;
    reg write_enable;
    reg read_enable;
    reg [7:0] data_in;
    wire [7:0] data_out;
    
    data_memory dut (
        .clk(clk),
        .address(address),
        .write_enable(write_enable),
        .read_enable(read_enable),
        .data_in(data_in),
        .data_out(data_out)
    );
    
    initial begin
        clk = 0;
        forever #5 clk = ~clk;
    end
    
    initial begin
        write_enable = 0;
        read_enable = 0;
        address = 0;
        data_in = 0;
        
        #20;
        
        // Test case 1: Write data to memory
        @(negedge clk);
        write_enable = 1;
        read_enable = 0;
        address = 8'h20;
        data_in = 8'hA5;
        @(posedge clk);
        @(negedge clk);
        write_enable = 0;
        
        // Test case 2: Read data from memory
        read_enable = 1;
        @(posedge clk);
        @(negedge clk);
        if (data_out === 8'hA5)
            $display("Test case 1 passed: Read correct data 0xA5 from address 0x20");
        else
            $display("Test case 1 failed: Expected 0xA5, got %h", data_out);
        
        // Test case 3: Write to different address
        write_enable = 1;
        read_enable = 0;
        address = 8'h55;
        data_in = 8'h3C;
        @(posedge clk);
        @(negedge clk);
        write_enable = 0;
        
        // Test case 4: Read from second address
        read_enable = 1;
        @(posedge clk);
        @(negedge clk);
        if (data_out === 8'h3C)
            $display("Test case 2 passed: Read correct data 0x3C from address 0x55");
        else
            $display("Test case 2 failed: Expected 0x3C, got %h", data_out);
        
        // Test case 5: Read from first address again
        address = 8'h20;
        @(posedge clk);
        @(negedge clk);
        if (data_out === 8'hA5)
            $display("Test case 3 passed: First written data preserved");
        else
            $display("Test case 3 failed: Expected 0xA5, got %h", data_out);
        
        // Test case 6: Test read without read_enable
        read_enable = 0;
        address = 8'h55;
        @(posedge clk);
        @(negedge clk);
        if (data_out !== 8'h3C)
            $display("Test case 4 passed: Data not read when read_enable is low");
        else
            $display("Test case 4 failed: Data should not have updated");
        
        // Test case 7: Test write without write_enable
        write_enable = 0;
        address = 8'h20;
        data_in = 8'hFF;
        @(posedge clk);
        read_enable = 1;
        @(posedge clk);
        @(negedge clk);
        if (data_out === 8'hA5)
            $display("Test case 5 passed: Write ignored when write_enable is low");
        else
            $display("Test case 5 failed: Expected 0xA5, got %h", data_out);
        
        // End simulation
        #20;
        $display("Simulation completed");
        $finish;
    end
endmodule

Harvard_Central_Processing_Unit.sim/sim_1/behav/xsim/data_memory_tb.vcd
$date
   Mon Nov  4 22:04:32 2024
$end
$version
  2018.2
$end
$timescale
  1ps
$end
$scope module data_memory_tb $end
$var reg 1 ! clk $end
$var reg 8 " address [7:0] $end
$var reg 1 # write_enable $end
$var reg 1 $ read_enable $end
$var reg 8 % data_in [7:0] $end
$var wire 8 & data_out [7:0] $end
$scope module dut $end
$var wire 1 ' clk $end
$var wire 8 ( address [7:0] $end
$var wire 1 ) write_enable $end
$var wire 1 * read_enable $end
$var wire 8 + data_in [7:0] $end
$var reg 8 , data_out [7:0] $end
$var integer 32 - i $end
$upscope $end
$upscope $end
$enddefinitions $end
#0
$dumpvars
0!
b0 "
0#
0$
b0 %
bx &
0'
b0 (
0)
0*
b0 +
bx ,
b100000000 -
$end
#5000
1!
1'
#10000
0!
0'
#15000
1!
1'
#20000
0!
b100000 "
1#
b10100101 %
0'
b100000 (
1)
b10100101 +
#25000
1!
1'
#30000
0!
0#
0'
0)
#35000
1!
1'
#40000
0!
0'
#45000
1!
1'
#50000
0!
1$
0'
1*
#55000
1!
b10100101 &
1'
b10100101 ,
#60000
0!
0'
#65000
1!
1'
#70000
0!
0'
#75000
1!
1'
#80000
0!
b1010101 "
1#
0$
b111100 %
0'
b1010101 (
1)
0*
b111100 +
#85000
1!
1'
#90000
0!
0#
0'
0)
#95000
1!
1'
#100000
0!
0'
#105000
1!
1'
#110000
0!
1$
0'
1*
#115000
1!
b111100 &
1'
b111100 ,
#120000
0!
0'
#125000
1!
1'
#130000
0!
0'
#135000
1!
1'
#140000
0!
b100000 "
0'
b100000 (
#145000
1!
b10100101 &
1'
b10100101 ,
#150000
0!
0'
#155000
1!
1'
#160000
0!
0'
#165000
1!
1'
#170000
0!
b1010101 "
0$
0'
b1010101 (
0*
#175000
1!
1'
#180000
0!
0'
#185000
1!
1'
#190000
0!
0'
#195000
1!
1'
#200000
0!
b100000 "
b11111111 %
0'
b100000 (
b11111111 +
#205000
1!
1$
1'
1*
